pyfsdb/__init__.py
pyfsdb/fsdb.py
pyfsdb/fsdb2parquet.~1~
pyfsdb/graph_utils.py
pyfsdb/obsolete/__init__.py
pyfsdb/obsolete/db2tex.py
pyfsdb/obsolete/dbaugment.py
pyfsdb/obsolete/dbcoluniq.py
pyfsdb/obsolete/dbdatetoepoch.py
pyfsdb/obsolete/dbensure.py
pyfsdb/obsolete/dbformat.py
pyfsdb/obsolete/dbfullpivot.py
pyfsdb/obsolete/dbheatmap.py
pyfsdb/obsolete/dbkeyedsort.py
pyfsdb/obsolete/dbnormalize.py
pyfsdb/obsolete/dbreescape.py
pyfsdb/obsolete/dbreversepivot.py
pyfsdb/obsolete/dbsplitter.py
pyfsdb/obsolete/dbsum.py
pyfsdb/obsolete/dbtopn.py
pyfsdb/obsolete/dbzerofill.py
pyfsdb/tests/support.py
pyfsdb/tests/test_add_types.py
pyfsdb/tests/test_column_name_setting.py
pyfsdb/tests/test_column_renames.py
pyfsdb/tests/test_coluniq.py
pyfsdb/tests/test_command_parsing.py
pyfsdb/tests/test_fsdb_class.py
pyfsdb/tests/test_json.py
pyfsdb/tests/test_label_shrink.py
pyfsdb/tests/test_missing_columns.py
pyfsdb/tests/test_msgpack.py
pyfsdb/tests/test_pdbaugment.py
pyfsdb/tests/test_pdbcdf.py
pyfsdb/tests/test_pdbj2.py.~1~
pyfsdb/tests/test_pdbjinja.py
pyfsdb/tests/test_pdbrow.py
pyfsdb/tests/test_pdbroweval.py
pyfsdb/tests/test_sql.py
pyfsdb/tests/test_sql.py.~1~
pyfsdb/tests/test_utf8.py
pyfsdb/tests/test_zero_fill.py
pyfsdb/tools/__init__.py
pyfsdb/tools/bro2fsdb.py
pyfsdb/tools/fsdb2json.py
pyfsdb/tools/fsdb2many.py
pyfsdb/tools/json2fsdb.py
pyfsdb/tools/msgpack2pdb.py
pyfsdb/tools/pdb2html.py
pyfsdb/tools/pdb2msgpack.py
pyfsdb/tools/pdb2sql.py
pyfsdb/tools/pdb2tex.py
pyfsdb/tools/pdb2to1.py
pyfsdb/tools/pdbaddtypes.py
pyfsdb/tools/pdbaugment.py
pyfsdb/tools/pdbbarplot.py
pyfsdb/tools/pdbcdf.py
pyfsdb/tools/pdbcoluniq.py
pyfsdb/tools/pdbdatetoepoch.py
pyfsdb/tools/pdbensure.py
pyfsdb/tools/pdbepochtodate.py
pyfsdb/tools/pdbfgrep.py
pyfsdb/tools/pdbformat.py
pyfsdb/tools/pdbfullpivot.py
pyfsdb/tools/pdbheatmap.py
pyfsdb/tools/pdbjinja.py
pyfsdb/tools/pdbkeyedsort.py
pyfsdb/tools/pdbnormalize.py
pyfsdb/tools/pdbpathtrack.py
pyfsdb/tools/pdbreescape.py
pyfsdb-2.7.dist-info/METADATA
pyfsdb-2.7.dist-info/WHEEL
pyfsdb-2.7.dist-info/entry_points.txt
pyfsdb-2.7.dist-info/licenses/LICENSE
pyfsdb-2.7.dist-info/RECORD
