Metadata-Version: 2.4
Name: pyfsdb
Version: 2.7
Summary: A python implementation of the flat-file streaming database
Project-URL: Homepage, https://github.com/hardaker/pyfsdb
Author-email: Wes Hardaker <opensource@hardakers.net>
License: MIT License
License-File: LICENSE
Classifier: Operating System :: OS Independent
Classifier: Programming Language :: Python :: 3
Requires-Python: >=3.6
